setup.py
sandbox/__init__.py
sandbox/ec2-prices.py
sandbox/finder.py
sandbox/index_overflow_test.py
sandbox/migrate_specific.py
usergrid_tools/__init__.py
usergrid_tools/library_check.py
usergrid_tools/general/__init__.py
usergrid_tools/general/deleter.py
usergrid_tools/general/url_tester.py
usergrid_tools/indexing/__init__.py
usergrid_tools/indexing/index_test.py
usergrid_tools/iterators/__init__.py
usergrid_tools/iterators/usergrid_cross_region_iterator.py
usergrid_tools/iterators/usergrid_iterator.py
usergrid_tools/migration/__init__.py
usergrid_tools/migration/usergrid_data_migrator.py
usergrid_tools/parse_importer/__init__.py
usergrid_tools/parse_importer/parse_importer.py
usergrid_utils.egg-info/PKG-INFO
usergrid_utils.egg-info/SOURCES.txt
usergrid_utils.egg-info/dependency_links.txt
usergrid_utils.egg-info/entry_points.txt
usergrid_utils.egg-info/requires.txt
usergrid_utils.egg-info/top_level.txt