Metadata-Version: 1.1
Name: usergrid-utils
Version: 0.0.2
Summary: Tools for working with Apache Usergrid
Home-page: http://usergrid.apache.org
Author: Jeff West
Author-email: jwest@apigee.com
License: UNKNOWN
Download-URL: https://codeload.github.com/jwest-apigee/usergrid-util-python/zip/v0.0.2
Platform: UNKNOWN
